Metadata-Version: 1.0
Name: tag2bio
Version: 0.4
Summary: A package created for translating tag formatted text to BIO formatted text.
Home-page: UNKNOWN
Author: UNKNOWN
Author-email: UNKNOWN
License: UNKNOWN
Platform: UNKNOWN
